{
  "model_type": "plm",
  "model_name": "google-bert/bert-base-multilingual-uncased",
  "atl": false,
  "context": true,
  "smoke_test": false,
  "training_size": 5000,
  "experiment": "seed",
  "prompt_template": "instruct",
  "epochs": 2,
  "learning_rate": 5e-05,
  "batch_size": 16,
  "max_grad_norm": 1.0,
  "weight_decay": 0.01,
  "quantization": true,
  "lang": "no",
  "run_dir": "/scratch/prj/inf_nlg_ai_detection/wcd/data/exp1/no/run_ih6peb",
  "model_dir": "",
  "notes": "",
  "train_log_step": 20,
  "prompt_extension": "",
  "max_length": 512,
  "seed": 2026,
  "metric": "f1",
  "setting": "main",
  "lang_setting": "main",
  "source_langs": [],
  "target_langs": [],
  "lang_settings": [],
  "cl_settings": [],
  "save_checkpoint": false,
  "from_checkpoint": false,
  "label_dist": {
    "train": {
      "0": 2494,
      "1": 2498
    },
    "dev": {
      "0": 250,
      "1": 250
    },
    "test": {
      "0": 250,
      "1": 250
    }
  },
  "date": "2025-12-22T16:10:42.575709",
  "duration": 0,
  "max_memory": 2.22652530670166,
  "bf16": true,
  "train_loss": [
    {
      "epoch": 1,
      "batch": 0,
      "loss": 0.695556640625
    },
    {
      "epoch": 1,
      "batch": 20,
      "loss": 0.69482421875
    },
    {
      "epoch": 1,
      "batch": 40,
      "loss": 0.681640625
    },
    {
      "epoch": 1,
      "batch": 60,
      "loss": 0.6732177734375
    },
    {
      "epoch": 1,
      "batch": 80,
      "loss": 0.6326904296875
    },
    {
      "epoch": 1,
      "batch": 100,
      "loss": 0.63214111328125
    },
    {
      "epoch": 1,
      "batch": 120,
      "loss": 0.5811767578125
    },
    {
      "epoch": 1,
      "batch": 140,
      "loss": 0.473876953125
    },
    {
      "epoch": 1,
      "batch": 160,
      "loss": 0.703857421875
    },
    {
      "epoch": 1,
      "batch": 180,
      "loss": 0.6314697265625
    },
    {
      "epoch": 1,
      "batch": 200,
      "loss": 0.5677490234375
    },
    {
      "epoch": 1,
      "batch": 220,
      "loss": 0.65411376953125
    },
    {
      "epoch": 1,
      "batch": 240,
      "loss": 0.748321533203125
    },
    {
      "epoch": 1,
      "batch": 260,
      "loss": 0.46539306640625
    },
    {
      "epoch": 1,
      "batch": 280,
      "loss": 0.5484619140625
    },
    {
      "epoch": 1,
      "batch": 300,
      "loss": 0.67559814453125
    },
    {
      "epoch": 2,
      "batch": 0,
      "loss": 0.5755615234375
    },
    {
      "epoch": 2,
      "batch": 20,
      "loss": 0.46490478515625
    },
    {
      "epoch": 2,
      "batch": 40,
      "loss": 0.4906005859375
    },
    {
      "epoch": 2,
      "batch": 60,
      "loss": 0.6346435546875
    },
    {
      "epoch": 2,
      "batch": 80,
      "loss": 0.76043701171875
    },
    {
      "epoch": 2,
      "batch": 100,
      "loss": 0.46405029296875
    },
    {
      "epoch": 2,
      "batch": 120,
      "loss": 0.62969970703125
    },
    {
      "epoch": 2,
      "batch": 140,
      "loss": 0.78314208984375
    },
    {
      "epoch": 2,
      "batch": 160,
      "loss": 0.4434814453125
    },
    {
      "epoch": 2,
      "batch": 180,
      "loss": 0.772216796875
    },
    {
      "epoch": 2,
      "batch": 200,
      "loss": 0.5914306640625
    },
    {
      "epoch": 2,
      "batch": 220,
      "loss": 0.51263427734375
    },
    {
      "epoch": 2,
      "batch": 240,
      "loss": 0.55010986328125
    },
    {
      "epoch": 2,
      "batch": 260,
      "loss": 0.610321044921875
    },
    {
      "epoch": 2,
      "batch": 280,
      "loss": 0.76409912109375
    },
    {
      "epoch": 2,
      "batch": 300,
      "loss": 0.4356689453125
    }
  ],
  "dev_loss": [
    {
      "epoch": 1,
      "batch": 0,
      "loss": 0.6951
    },
    {
      "epoch": 1,
      "batch": 60,
      "loss": 0.6618
    },
    {
      "epoch": 1,
      "batch": 120,
      "loss": 0.6224
    },
    {
      "epoch": 1,
      "batch": 180,
      "loss": 0.6036
    },
    {
      "epoch": 1,
      "batch": 240,
      "loss": 0.6203
    },
    {
      "epoch": 1,
      "batch": 300,
      "loss": 0.6031
    },
    {
      "epoch": 2,
      "batch": 0,
      "loss": 0.5982
    },
    {
      "epoch": 2,
      "batch": 60,
      "loss": 0.6124
    },
    {
      "epoch": 2,
      "batch": 120,
      "loss": 0.626
    },
    {
      "epoch": 2,
      "batch": 180,
      "loss": 0.613
    },
    {
      "epoch": 2,
      "batch": 240,
      "loss": 0.6108
    },
    {
      "epoch": 2,
      "batch": 300,
      "loss": 0.6106
    }
  ],
  "dev_metrics": [
    {
      "epoch": 1,
      "metrics": {
        "accuracy": 0.664,
        "f1": 0.6455696202531646,
        "tp": 153,
        "fp": 71,
        "tn": 179,
        "fn": 97,
        "n_total": 500
      }
    },
    {
      "epoch": 2,
      "metrics": {
        "accuracy": 0.658,
        "f1": 0.6338329764453962,
        "tp": 148,
        "fp": 69,
        "tn": 181,
        "fn": 102,
        "n_total": 500
      }
    }
  ],
  "test_metrics": [
    {
      "epoch": 1,
      "metrics": {
        "accuracy": 0.68,
        "f1": 0.6638655462184874,
        "tp": 158,
        "fp": 68,
        "tn": 182,
        "fn": 92,
        "n_total": 500
      }
    },
    {
      "epoch": 2,
      "metrics": {
        "accuracy": 0.676,
        "f1": 0.6567796610169492,
        "tp": 155,
        "fp": 67,
        "tn": 183,
        "fn": 95,
        "n_total": 500
      }
    }
  ]
}