{
  "model_type": "slm",
  "model_name": "meta-llama/Llama-3.1-8B-Instruct",
  "atl": false,
  "context": true,
  "smoke_test": false,
  "training_size": 5000,
  "experiment": "binary",
  "prompt_template": "instruct",
  "epochs": 4,
  "learning_rate": 0.0005,
  "batch_size": 16,
  "max_grad_norm": 0.5,
  "weight_decay": 0.01,
  "quantization": true,
  "lang": "ro",
  "run_dir": "/scratch/prj/inf_nlg_ai_detection/wcd/data/exp1/ro/run_Latngz",
  "notes": "testing 1 grad norm",
  "train_log_step": 20,
  "prompt_extension": "",
  "max_length": 512,
  "seed": 42,
  "training_langs": [],
  "test_lang": "",
  "model_dir": "",
  "save_checkpoint": false,
  "from_checkpoint": false,
  "label_dist": {
    "train": {
      "0": 2495,
      "1": 2494
    },
    "dev": {
      "0": 250,
      "1": 249
    },
    "test": {
      "0": 249,
      "1": 247
    }
  },
  "date": "2025-12-15T14:00:14.034143",
  "duration": 68,
  "max_memory": 25.028127670288086,
  "bf16": true,
  "train_loss": [
    {
      "epoch": 1,
      "batch": 0,
      "loss": 3.1269800662994385
    },
    {
      "epoch": 1,
      "batch": 20,
      "loss": 1.0240072011947632
    },
    {
      "epoch": 1,
      "batch": 40,
      "loss": 1.0854524374008179
    },
    {
      "epoch": 1,
      "batch": 60,
      "loss": 0.9474354386329651
    },
    {
      "epoch": 1,
      "batch": 80,
      "loss": 1.0338414907455444
    },
    {
      "epoch": 1,
      "batch": 100,
      "loss": 1.0961750745773315
    },
    {
      "epoch": 1,
      "batch": 120,
      "loss": 0.9976063370704651
    },
    {
      "epoch": 1,
      "batch": 140,
      "loss": 0.9820948243141174
    },
    {
      "epoch": 1,
      "batch": 160,
      "loss": 0.9147040843963623
    },
    {
      "epoch": 1,
      "batch": 180,
      "loss": 0.9239642024040222
    },
    {
      "epoch": 1,
      "batch": 200,
      "loss": 0.9623314142227173
    },
    {
      "epoch": 1,
      "batch": 220,
      "loss": 0.9463104009628296
    },
    {
      "epoch": 1,
      "batch": 240,
      "loss": 0.9340679049491882
    },
    {
      "epoch": 1,
      "batch": 260,
      "loss": 0.9125778079032898
    },
    {
      "epoch": 1,
      "batch": 280,
      "loss": 1.0110976696014404
    },
    {
      "epoch": 1,
      "batch": 300,
      "loss": 1.026423454284668
    },
    {
      "epoch": 2,
      "batch": 0,
      "loss": 0.6723864078521729
    },
    {
      "epoch": 2,
      "batch": 20,
      "loss": 0.7444639801979065
    },
    {
      "epoch": 2,
      "batch": 40,
      "loss": 0.6506274342536926
    },
    {
      "epoch": 2,
      "batch": 60,
      "loss": 0.6246397495269775
    },
    {
      "epoch": 2,
      "batch": 80,
      "loss": 0.7707444429397583
    },
    {
      "epoch": 2,
      "batch": 100,
      "loss": 0.6753453612327576
    },
    {
      "epoch": 2,
      "batch": 120,
      "loss": 0.7190129160881042
    },
    {
      "epoch": 2,
      "batch": 140,
      "loss": 0.7938622832298279
    },
    {
      "epoch": 2,
      "batch": 160,
      "loss": 0.6527523994445801
    },
    {
      "epoch": 2,
      "batch": 180,
      "loss": 0.8031163811683655
    },
    {
      "epoch": 2,
      "batch": 200,
      "loss": 0.6988348960876465
    },
    {
      "epoch": 2,
      "batch": 220,
      "loss": 0.7615163326263428
    },
    {
      "epoch": 2,
      "batch": 240,
      "loss": 0.7051813006401062
    },
    {
      "epoch": 2,
      "batch": 260,
      "loss": 0.7577593922615051
    },
    {
      "epoch": 2,
      "batch": 280,
      "loss": 0.6789018511772156
    },
    {
      "epoch": 2,
      "batch": 300,
      "loss": 0.68120276927948
    },
    {
      "epoch": 3,
      "batch": 0,
      "loss": 0.4190198481082916
    },
    {
      "epoch": 3,
      "batch": 20,
      "loss": 0.399810791015625
    },
    {
      "epoch": 3,
      "batch": 40,
      "loss": 0.4116983115673065
    },
    {
      "epoch": 3,
      "batch": 60,
      "loss": 0.38329195976257324
    },
    {
      "epoch": 3,
      "batch": 80,
      "loss": 0.40292033553123474
    },
    {
      "epoch": 3,
      "batch": 100,
      "loss": 0.3236551880836487
    },
    {
      "epoch": 3,
      "batch": 120,
      "loss": 0.45127415657043457
    },
    {
      "epoch": 3,
      "batch": 140,
      "loss": 0.3716724216938019
    },
    {
      "epoch": 3,
      "batch": 160,
      "loss": 0.4076578915119171
    },
    {
      "epoch": 3,
      "batch": 180,
      "loss": 0.3979843854904175
    },
    {
      "epoch": 3,
      "batch": 200,
      "loss": 0.42409682273864746
    },
    {
      "epoch": 3,
      "batch": 220,
      "loss": 0.36459100246429443
    },
    {
      "epoch": 3,
      "batch": 240,
      "loss": 0.4029817581176758
    },
    {
      "epoch": 3,
      "batch": 260,
      "loss": 0.44306349754333496
    },
    {
      "epoch": 3,
      "batch": 280,
      "loss": 0.3906596601009369
    },
    {
      "epoch": 3,
      "batch": 300,
      "loss": 0.44857078790664673
    },
    {
      "epoch": 4,
      "batch": 0,
      "loss": 0.23919355869293213
    },
    {
      "epoch": 4,
      "batch": 20,
      "loss": 0.1901044398546219
    },
    {
      "epoch": 4,
      "batch": 40,
      "loss": 0.21358349919319153
    },
    {
      "epoch": 4,
      "batch": 60,
      "loss": 0.18222704529762268
    },
    {
      "epoch": 4,
      "batch": 80,
      "loss": 0.19045239686965942
    },
    {
      "epoch": 4,
      "batch": 100,
      "loss": 0.19096380472183228
    },
    {
      "epoch": 4,
      "batch": 120,
      "loss": 0.2140405774116516
    },
    {
      "epoch": 4,
      "batch": 140,
      "loss": 0.17012980580329895
    },
    {
      "epoch": 4,
      "batch": 160,
      "loss": 0.19935624301433563
    },
    {
      "epoch": 4,
      "batch": 180,
      "loss": 0.19860206544399261
    },
    {
      "epoch": 4,
      "batch": 200,
      "loss": 0.16958610713481903
    },
    {
      "epoch": 4,
      "batch": 220,
      "loss": 0.20660589635372162
    },
    {
      "epoch": 4,
      "batch": 240,
      "loss": 0.19036424160003662
    },
    {
      "epoch": 4,
      "batch": 260,
      "loss": 0.21783803403377533
    },
    {
      "epoch": 4,
      "batch": 280,
      "loss": 0.20158590376377106
    },
    {
      "epoch": 4,
      "batch": 300,
      "loss": 0.1896543800830841
    }
  ],
  "dev_loss": [
    {
      "epoch": 1,
      "batch": 0,
      "loss": 3.0109
    },
    {
      "epoch": 1,
      "batch": 60,
      "loss": 1.0447
    },
    {
      "epoch": 1,
      "batch": 120,
      "loss": 1.0454
    },
    {
      "epoch": 1,
      "batch": 180,
      "loss": 1.0482
    },
    {
      "epoch": 1,
      "batch": 240,
      "loss": 1.0511
    },
    {
      "epoch": 1,
      "batch": 300,
      "loss": 1.0452
    },
    {
      "epoch": 2,
      "batch": 0,
      "loss": 1.0531
    },
    {
      "epoch": 2,
      "batch": 60,
      "loss": 1.0938
    },
    {
      "epoch": 2,
      "batch": 120,
      "loss": 1.0934
    },
    {
      "epoch": 2,
      "batch": 180,
      "loss": 1.1013
    },
    {
      "epoch": 2,
      "batch": 240,
      "loss": 1.0909
    },
    {
      "epoch": 2,
      "batch": 300,
      "loss": 1.09
    },
    {
      "epoch": 3,
      "batch": 0,
      "loss": 1.0968
    },
    {
      "epoch": 3,
      "batch": 60,
      "loss": 1.1968
    },
    {
      "epoch": 3,
      "batch": 120,
      "loss": 1.1953
    },
    {
      "epoch": 3,
      "batch": 180,
      "loss": 1.2063
    },
    {
      "epoch": 3,
      "batch": 240,
      "loss": 1.2099
    },
    {
      "epoch": 3,
      "batch": 300,
      "loss": 1.1928
    },
    {
      "epoch": 4,
      "batch": 0,
      "loss": 1.2205
    },
    {
      "epoch": 4,
      "batch": 60,
      "loss": 1.3576
    },
    {
      "epoch": 4,
      "batch": 120,
      "loss": 1.3696
    },
    {
      "epoch": 4,
      "batch": 180,
      "loss": 1.3654
    },
    {
      "epoch": 4,
      "batch": 240,
      "loss": 1.3708
    },
    {
      "epoch": 4,
      "batch": 300,
      "loss": 1.3721
    }
  ],
  "dev_metrics": [
    {
      "epoch": 1,
      "metrics": {
        "accuracy": 0.6152304609218436,
        "f1": 0.6831683168316832,
        "tp": 207,
        "fp": 150,
        "tn": 100,
        "fn": 42,
        "n_valid": 499,
        "n_total": 499
      }
    },
    {
      "epoch": 2,
      "metrics": {
        "accuracy": 0.7014028056112225,
        "f1": 0.7245841035120147,
        "tp": 196,
        "fp": 96,
        "tn": 154,
        "fn": 53,
        "n_valid": 499,
        "n_total": 499
      }
    },
    {
      "epoch": 3,
      "metrics": {
        "accuracy": 0.6332665330661322,
        "f1": 0.6965174129353234,
        "tp": 210,
        "fp": 144,
        "tn": 106,
        "fn": 39,
        "n_valid": 499,
        "n_total": 499
      }
    },
    {
      "epoch": 4,
      "metrics": {
        "accuracy": 0.6452905811623246,
        "f1": 0.7074380165289256,
        "tp": 214,
        "fp": 142,
        "tn": 108,
        "fn": 35,
        "n_valid": 499,
        "n_total": 499
      }
    }
  ],
  "test_metrics": [
    {
      "epoch": 1,
      "metrics": {
        "accuracy": 0.7399193548387096,
        "f1": 0.7675675675675676,
        "tp": 213,
        "fp": 95,
        "tn": 154,
        "fn": 34,
        "n_valid": 496,
        "n_total": 496
      }
    },
    {
      "epoch": 2,
      "metrics": {
        "accuracy": 0.7459677419354839,
        "f1": 0.75,
        "tp": 189,
        "fp": 68,
        "tn": 181,
        "fn": 58,
        "n_valid": 496,
        "n_total": 496
      }
    },
    {
      "epoch": 3,
      "metrics": {
        "accuracy": 0.7580645161290323,
        "f1": 0.7894736842105263,
        "tp": 225,
        "fp": 98,
        "tn": 151,
        "fn": 22,
        "n_valid": 496,
        "n_total": 496
      }
    },
    {
      "epoch": 4,
      "metrics": {
        "accuracy": 0.7258064516129032,
        "f1": 0.7562724014336918,
        "tp": 211,
        "fp": 100,
        "tn": 149,
        "fn": 36,
        "n_valid": 496,
        "n_total": 496
      }
    }
  ]
}