{
  "model_type": "plm",
  "model_name": "google-bert/bert-base-multilingual-uncased",
  "atl": false,
  "context": true,
  "smoke_test": false,
  "training_size": 5000,
  "experiment": "seed",
  "prompt_template": "instruct",
  "epochs": 2,
  "learning_rate": 5e-05,
  "batch_size": 32,
  "max_grad_norm": 1.0,
  "weight_decay": 0.01,
  "quantization": true,
  "lang": "tr",
  "run_dir": "/scratch/prj/inf_nlg_ai_detection/wcd/data/exp1/tr/run_aPAnl5",
  "model_dir": "",
  "notes": "",
  "train_log_step": 20,
  "prompt_extension": "",
  "max_length": 512,
  "seed": 2025,
  "metric": "f1",
  "setting": "main",
  "lang_setting": "main",
  "source_langs": [],
  "target_langs": [],
  "lang_settings": [],
  "cl_settings": [],
  "save_checkpoint": false,
  "from_checkpoint": false,
  "label_dist": {
    "train": {
      "0": 2491,
      "1": 2476
    },
    "dev": {
      "0": 250,
      "1": 250
    },
    "test": {
      "0": 250,
      "1": 250
    }
  },
  "date": "2025-12-22T15:23:18.254791",
  "duration": 0,
  "max_memory": 3.838460922241211,
  "bf16": true,
  "train_loss": [
    {
      "epoch": 1,
      "batch": 0,
      "loss": 0.6942138671875
    },
    {
      "epoch": 1,
      "batch": 20,
      "loss": 0.573333740234375
    },
    {
      "epoch": 1,
      "batch": 40,
      "loss": 0.47190093994140625
    },
    {
      "epoch": 1,
      "batch": 60,
      "loss": 0.35193634033203125
    },
    {
      "epoch": 1,
      "batch": 80,
      "loss": 0.54241943359375
    },
    {
      "epoch": 1,
      "batch": 100,
      "loss": 0.5236282348632812
    },
    {
      "epoch": 1,
      "batch": 120,
      "loss": 0.36130523681640625
    },
    {
      "epoch": 1,
      "batch": 140,
      "loss": 0.4151115417480469
    },
    {
      "epoch": 2,
      "batch": 0,
      "loss": 0.3337516784667969
    },
    {
      "epoch": 2,
      "batch": 20,
      "loss": 0.2667522430419922
    },
    {
      "epoch": 2,
      "batch": 40,
      "loss": 0.3021087646484375
    },
    {
      "epoch": 2,
      "batch": 60,
      "loss": 0.36620330810546875
    },
    {
      "epoch": 2,
      "batch": 80,
      "loss": 0.3707542419433594
    },
    {
      "epoch": 2,
      "batch": 100,
      "loss": 0.6343002319335938
    },
    {
      "epoch": 2,
      "batch": 120,
      "loss": 0.2868690490722656
    },
    {
      "epoch": 2,
      "batch": 140,
      "loss": 0.22980880737304688
    }
  ],
  "dev_loss": [
    {
      "epoch": 1,
      "batch": 0,
      "loss": 0.697
    },
    {
      "epoch": 1,
      "batch": 60,
      "loss": 0.5061
    },
    {
      "epoch": 1,
      "batch": 120,
      "loss": 0.5308
    },
    {
      "epoch": 2,
      "batch": 0,
      "loss": 0.4958
    },
    {
      "epoch": 2,
      "batch": 60,
      "loss": 0.5129
    },
    {
      "epoch": 2,
      "batch": 120,
      "loss": 0.5094
    }
  ],
  "dev_metrics": [
    {
      "epoch": 1,
      "metrics": {
        "accuracy": 0.762,
        "f1": 0.7824497257769653,
        "tp": 214,
        "fp": 83,
        "tn": 167,
        "fn": 36,
        "n_total": 500
      }
    },
    {
      "epoch": 2,
      "metrics": {
        "accuracy": 0.768,
        "f1": 0.7867647058823529,
        "tp": 214,
        "fp": 80,
        "tn": 170,
        "fn": 36,
        "n_total": 500
      }
    }
  ],
  "test_metrics": [
    {
      "epoch": 1,
      "metrics": {
        "accuracy": 0.708,
        "f1": 0.7392857142857143,
        "tp": 207,
        "fp": 103,
        "tn": 147,
        "fn": 43,
        "n_total": 500
      }
    },
    {
      "epoch": 2,
      "metrics": {
        "accuracy": 0.708,
        "f1": 0.7420494699646644,
        "tp": 210,
        "fp": 106,
        "tn": 144,
        "fn": 40,
        "n_total": 500
      }
    }
  ]
}