{
  "model_type": "slm",
  "model_name": "CohereLabs/aya-expanse-8b",
  "atl": false,
  "context": true,
  "smoke_test": false,
  "training_size": 5000,
  "experiment": "binary",
  "prompt_template": "instruct",
  "epochs": 4,
  "learning_rate": 5e-05,
  "batch_size": 16,
  "max_grad_norm": 1.0,
  "weight_decay": 0.01,
  "quantization": true,
  "lang": "ru",
  "run_dir": "/scratch/prj/inf_nlg_ai_detection/wcd/data/exp1/ru/run_5TgxF1",
  "model_dir": "",
  "notes": "",
  "train_log_step": 20,
  "prompt_extension": "",
  "max_length": 512,
  "seed": 42,
  "metric": "f1",
  "setting": "main",
  "lang_setting": "main",
  "source_langs": [],
  "target_langs": [],
  "lang_settings": [],
  "cl_settings": [],
  "save_checkpoint": false,
  "from_checkpoint": false,
  "label_dist": {
    "train": {
      "0": 2198,
      "1": 1678
    },
    "dev": {
      "0": 250,
      "1": 250
    },
    "test": {
      "0": 249,
      "1": 250
    }
  },
  "date": "2025-12-23T17:35:57.668980",
  "duration": 44,
  "max_memory": 26.91934823989868,
  "bf16": true,
  "train_loss": [
    {
      "epoch": 1,
      "batch": 0,
      "loss": 17.175996780395508
    },
    {
      "epoch": 1,
      "batch": 20,
      "loss": 12.378473281860352
    },
    {
      "epoch": 1,
      "batch": 40,
      "loss": 7.33261775970459
    },
    {
      "epoch": 1,
      "batch": 60,
      "loss": 6.377222061157227
    },
    {
      "epoch": 1,
      "batch": 80,
      "loss": 6.252947807312012
    },
    {
      "epoch": 1,
      "batch": 100,
      "loss": 6.197539806365967
    },
    {
      "epoch": 1,
      "batch": 120,
      "loss": 6.107646465301514
    },
    {
      "epoch": 1,
      "batch": 140,
      "loss": 5.886545181274414
    },
    {
      "epoch": 1,
      "batch": 160,
      "loss": 5.856250286102295
    },
    {
      "epoch": 1,
      "batch": 180,
      "loss": 6.006841659545898
    },
    {
      "epoch": 1,
      "batch": 200,
      "loss": 5.8436126708984375
    },
    {
      "epoch": 1,
      "batch": 220,
      "loss": 5.581341743469238
    },
    {
      "epoch": 1,
      "batch": 240,
      "loss": 5.951062202453613
    },
    {
      "epoch": 2,
      "batch": 0,
      "loss": 5.810265064239502
    },
    {
      "epoch": 2,
      "batch": 20,
      "loss": 5.886840343475342
    },
    {
      "epoch": 2,
      "batch": 40,
      "loss": 5.7615437507629395
    },
    {
      "epoch": 2,
      "batch": 60,
      "loss": 5.828369617462158
    },
    {
      "epoch": 2,
      "batch": 80,
      "loss": 5.913760185241699
    },
    {
      "epoch": 2,
      "batch": 100,
      "loss": 5.912564754486084
    },
    {
      "epoch": 2,
      "batch": 120,
      "loss": 5.757533550262451
    },
    {
      "epoch": 2,
      "batch": 140,
      "loss": 5.752988338470459
    },
    {
      "epoch": 2,
      "batch": 160,
      "loss": 5.890415668487549
    },
    {
      "epoch": 2,
      "batch": 180,
      "loss": 5.776614665985107
    },
    {
      "epoch": 2,
      "batch": 200,
      "loss": 5.945104122161865
    },
    {
      "epoch": 2,
      "batch": 220,
      "loss": 5.937077045440674
    },
    {
      "epoch": 2,
      "batch": 240,
      "loss": 5.222448348999023
    },
    {
      "epoch": 3,
      "batch": 0,
      "loss": 5.737362384796143
    },
    {
      "epoch": 3,
      "batch": 20,
      "loss": 5.891653537750244
    },
    {
      "epoch": 3,
      "batch": 40,
      "loss": 5.751502513885498
    },
    {
      "epoch": 3,
      "batch": 60,
      "loss": 5.810834884643555
    },
    {
      "epoch": 3,
      "batch": 80,
      "loss": 5.7788848876953125
    },
    {
      "epoch": 3,
      "batch": 100,
      "loss": 5.750487804412842
    },
    {
      "epoch": 3,
      "batch": 120,
      "loss": 5.866997241973877
    },
    {
      "epoch": 3,
      "batch": 140,
      "loss": 5.78153133392334
    },
    {
      "epoch": 3,
      "batch": 160,
      "loss": 5.6837477684021
    },
    {
      "epoch": 3,
      "batch": 180,
      "loss": 5.814916133880615
    },
    {
      "epoch": 3,
      "batch": 200,
      "loss": 5.616384506225586
    },
    {
      "epoch": 3,
      "batch": 220,
      "loss": 5.890543460845947
    },
    {
      "epoch": 3,
      "batch": 240,
      "loss": 5.7662882804870605
    },
    {
      "epoch": 4,
      "batch": 0,
      "loss": 5.627353191375732
    },
    {
      "epoch": 4,
      "batch": 20,
      "loss": 5.686956405639648
    },
    {
      "epoch": 4,
      "batch": 40,
      "loss": 5.608090877532959
    },
    {
      "epoch": 4,
      "batch": 60,
      "loss": 5.644250869750977
    },
    {
      "epoch": 4,
      "batch": 80,
      "loss": 5.852430820465088
    },
    {
      "epoch": 4,
      "batch": 100,
      "loss": 5.735814094543457
    },
    {
      "epoch": 4,
      "batch": 120,
      "loss": 5.840473651885986
    },
    {
      "epoch": 4,
      "batch": 140,
      "loss": 5.914320468902588
    },
    {
      "epoch": 4,
      "batch": 160,
      "loss": 5.797703742980957
    },
    {
      "epoch": 4,
      "batch": 180,
      "loss": 5.7918925285339355
    },
    {
      "epoch": 4,
      "batch": 200,
      "loss": 5.912074089050293
    },
    {
      "epoch": 4,
      "batch": 220,
      "loss": 5.725703239440918
    },
    {
      "epoch": 4,
      "batch": 240,
      "loss": 5.861645221710205
    }
  ],
  "dev_loss": [
    {
      "epoch": 1,
      "batch": 0,
      "loss": 15.1258
    },
    {
      "epoch": 1,
      "batch": 60,
      "loss": 6.5589
    },
    {
      "epoch": 1,
      "batch": 120,
      "loss": 6.193
    },
    {
      "epoch": 1,
      "batch": 180,
      "loss": 6.0926
    },
    {
      "epoch": 1,
      "batch": 240,
      "loss": 6.0911
    },
    {
      "epoch": 2,
      "batch": 0,
      "loss": 6.0902
    },
    {
      "epoch": 2,
      "batch": 60,
      "loss": 6.0491
    },
    {
      "epoch": 2,
      "batch": 120,
      "loss": 6.0289
    },
    {
      "epoch": 2,
      "batch": 180,
      "loss": 5.9942
    },
    {
      "epoch": 2,
      "batch": 240,
      "loss": 6.0156
    },
    {
      "epoch": 3,
      "batch": 0,
      "loss": 6.0099
    },
    {
      "epoch": 3,
      "batch": 60,
      "loss": 5.9886
    },
    {
      "epoch": 3,
      "batch": 120,
      "loss": 5.9834
    },
    {
      "epoch": 3,
      "batch": 180,
      "loss": 5.962
    },
    {
      "epoch": 3,
      "batch": 240,
      "loss": 5.9612
    },
    {
      "epoch": 4,
      "batch": 0,
      "loss": 5.9747
    },
    {
      "epoch": 4,
      "batch": 60,
      "loss": 5.975
    },
    {
      "epoch": 4,
      "batch": 120,
      "loss": 5.9594
    },
    {
      "epoch": 4,
      "batch": 180,
      "loss": 5.9815
    },
    {
      "epoch": 4,
      "batch": 240,
      "loss": 5.9881
    }
  ],
  "dev_metrics": [
    {
      "epoch": 1,
      "metrics": {
        "accuracy": 0.4969818913480885,
        "f1": 0.6621621621621622,
        "tp": 245,
        "fp": 245,
        "tn": 2,
        "fn": 5,
        "n_valid": 497,
        "n_total": 500
      }
    },
    {
      "epoch": 2,
      "metrics": {
        "accuracy": 0.596,
        "f1": 0.6823899371069182,
        "tp": 217,
        "fp": 169,
        "tn": 81,
        "fn": 33,
        "n_valid": 500,
        "n_total": 500
      }
    },
    {
      "epoch": 3,
      "metrics": {
        "accuracy": 0.6492985971943888,
        "f1": 0.6153846153846154,
        "tp": 140,
        "fp": 65,
        "tn": 184,
        "fn": 110,
        "n_valid": 499,
        "n_total": 500
      }
    },
    {
      "epoch": 4,
      "metrics": {
        "accuracy": 0.5938144329896907,
        "f1": 0.6964560862865947,
        "tp": 226,
        "fp": 174,
        "tn": 62,
        "fn": 23,
        "n_valid": 485,
        "n_total": 500
      }
    }
  ],
  "test_metrics": [
    {
      "epoch": 1,
      "metrics": {
        "accuracy": 0.5130784708249497,
        "f1": 0.670299727520436,
        "tp": 246,
        "fp": 238,
        "tn": 9,
        "fn": 4,
        "n_valid": 497,
        "n_total": 499
      }
    },
    {
      "epoch": 2,
      "metrics": {
        "accuracy": 0.5769230769230769,
        "f1": 0.669826224328594,
        "tp": 212,
        "fp": 171,
        "tn": 73,
        "fn": 38,
        "n_valid": 494,
        "n_total": 499
      }
    },
    {
      "epoch": 3,
      "metrics": {
        "accuracy": 0.631578947368421,
        "f1": 0.6043478260869565,
        "tp": 139,
        "fp": 72,
        "tn": 173,
        "fn": 110,
        "n_valid": 494,
        "n_total": 499
      }
    },
    {
      "epoch": 4,
      "metrics": {
        "accuracy": 0.6071428571428571,
        "f1": 0.705511811023622,
        "tp": 224,
        "fp": 162,
        "tn": 65,
        "fn": 25,
        "n_valid": 476,
        "n_total": 499
      }
    }
  ]
}